[
    {
      "date": "2026-01-26",
      "time": "8:30pm – 10pm",
      "venue": "Blondie's Bar",
      "event": "",
      "link": "",
      "location": "540 Valencia St, San Francisco, CA"
    }, 
    {
      "date": "2026-03-17",
      "time": "8pm – 11pm",
      "venue": "Alhambra Irish House",
      "event": "St. Patrick's Day",
      "link": "",
      "location": "831 Main Street, Redwood City, CA"
    },    
    {
      "date": "2025-12-12",
      "time": "7:40pm – 8:20pm",
      "venue": "Devil's Canyon Brewing Co.",
      "event": "20th Annual Holiday Hootenanny!",
      "link": "https://tockify.com/devilscanyon/detail/753/1765584000000",
      "location": "935 Washington Street, San Carlos, CA"
    },
    {
      "date": "2026-03-27",
      "time": "8pm – 11pm",
      "venue": "Alhambra Irish House",
      "event": "",
      "link": "",
      "location": "831 Main Street, Redwood City, CA"
    },
    {
      "date": "2026-1-30",
      "time": "7 - 8:45pm",
      "venue": "Vinyl Room",
      "event": "Album Release Show! Stick around after 9pm for a party!",
      "link": "",
      "location": "221 Park Rd, Burlingame, CA 94010"
    },
    {
      "date": "2025-12-03",
      "time": "7:30 - 9pm",
      "venue": "Pioneer Saloon",
      "event": "Stick around for Michael O'Fiesh (with TRC guests?) - 9 - 10:30pm!",
      "link": "",
      "location": "2925 Woodside Rd, Woodside, CA 94062"
    },
    {
      "date": "2026-01-24",
      "time": "5:30 - 8:30pm",
      "venue": "Sam's Chowder House",
      "event": "",
      "link": "",
      "location": "4210 CA-1, Half Moon Bay, CA"
    },
    {
      "date": "2025-11-15",
      "time": "7pm – 10pm",
      "venue": "Alhambra Irish House",
      "event": "",
      "link": "",
      "location": "831 Main Street, Redwood City, CA"
    },
    {
      "date": "2025-11-14",
      "time": "9pm – 10pm",
      "venue": "Arbor Live, Stanford University",
      "event": "",
      "link": "",
      "location": "459 Lagunita Dr, Stanford, CA"
    },
    {
      "date": "2025-11-04",
      "time": "5:45 - 9:45pm",
      "venue": "Filoli",
      "event": "Tickets: Filoli Nightfall",
      "link": "https://filoli.org/nightfall/",
      "location": "86 Cañada Rd, Woodside, CA"
    },
    {
      "date": "2025-10-28",
      "time": "5:45 - 9:45pm",
      "venue": "Filoli",
      "event": "Tickets: Filoli Nightfall",
      "link": "https://filoli.org/nightfall/",
      "location": "Woodside, CA"
    },
    {
      "date": "2025-10-21",
      "time": "5:45 - 9:45pm",
      "venue": "Filoli",
      "event": "Tickets: Filoli Nightfall",
      "link": "https://filoli.org/nightfall/",
      "location": "86 Cañada Rd, Woodside, CA"
    },
    {
      "date": "2025-10-19",
      "time": "5:45 - 9:45pm",
      "venue": "Filoli",
      "event": "Tickets: Filoli Nightfall",
      "link": "https://filoli.org/nightfall/",
      "location": "86 Cañada Rd, Woodside, CA"
    },
    {
      "date": "2025-10-15",
      "time": "5:45 - 9:45pm",
      "venue": "Filoli",
      "event": "Tickets: Filoli Nightfall",
      "link": "https://filoli.org/nightfall/",
      "location": "86 Cañada Rd, Woodside, CA"
    },
    {
      "date": "2025-09-27",
      "time": "5:30pm – 9:30pm",
      "venue": "Roaring Camp Railroads",
      "event": "Starlight Evening Dinner Party",
      "link": "https://roaringcamp.com/events",
      "location": "Felton, CA"
    },
    {
      "date": "2025-09-20",
      "time": "11:30am – 1:30pm",
      "venue": "Salesforce Park",
      "event": "Bluegrass Breeze",
      "link": "https://www.tjpa.org/media/39988/download?inline",
      "location": "425 Mission St, San Francisco, CA"
    },
    {
      "date": "2025-09-13",
      "time": "9pm – 12am",
      "venue": "Alhambra Irish House",
      "event": "",
      "link": "",
      "location": "831 Main Street, Redwood City, CA"
    },
    {
      "date": "2025-05-23",
      "time": "",
      "venue": "Arbor Live, Stanford University",
      "event": "",
      "link": "",
      "location": "Palo Alto, CA"
    },
    {
      "date": "2025-05-09",
      "time": "",
      "venue": "Arbor Live, Stanford University",
      "event": "",
      "link": "",
      "location": "Palo Alto, CA"
    },
    {
      "date": "2025-05-04",
      "time": "",
      "venue": "Socks and Sandals",
      "event": "",
      "link": "",
      "location": "Palo Alto, CA"
    },
    {
      "date": "2025-04-19",
      "time": "",
      "venue": "Freewheel Brewing Co.",
      "event": "",
      "link": "",
      "location": "Redwood City, CA"
    },
    {
      "date": "2025-03-01",
      "time": "",
      "venue": "The Magnolia of Millbrae",
      "event": "",
      "link": "",
      "location": "Millbrae, CA"
    },
    {
      "date": "2025-01-26",
      "time": "",
      "venue": "O'Reilly's Pub",
      "event": "",
      "link": "",
      "location": "San Francisco, CA"
    },
    {
      "date": "2025-01-25",
      "time": "",
      "venue": "Red Rock Coffee",
      "event": "",
      "link": "",
      "location": "Mountain View, CA"
    },
    {
      "date": "2024-10-04",
      "time": "",
      "venue": "Arbor Live, Stanford University",
      "event": "",
      "link": "",
      "location": "Palo Alto, CA"
    },
    {
      "date": "2024-08-17",
      "time": "",
      "venue": "The Magnolia of Millbrae",
      "event": "",
      "link": "",
      "location": "Millbrae, CA"
    },
    {
      "date": "2024-06-21",
      "time": "",
      "venue": "Telluride Bluegrass Festival (Family Tent)",
      "event": "",
      "link": "",
      "location": "Telluride, CO"
    },
    {
      "date": "2024-06-10",
      "time": "",
      "venue": "Stanford Farm",
      "event": "",
      "link": "",
      "location": "Palo Alto, CA"
    }
  ]  
